setup.py
wayround_org/http/__init__.py
wayround_org/http/cookies.py
wayround_org/http/message.py
wayround_org/http/server.py
wayround_org_http.egg-info/PKG-INFO
wayround_org_http.egg-info/SOURCES.txt
wayround_org_http.egg-info/dependency_links.txt
wayround_org_http.egg-info/requires.txt
wayround_org_http.egg-info/top_level.txt