Metadata-Version: 1.1
Name: wayround-org-http
Version: 0.5.3
Summary: http realisation
Home-page: https://github.com/AnimusPEXUS/wayround_org_http
Author: Alexey Gorshkov
Author-email: animus@wayround.org
License: UNKNOWN
Platform: UNKNOWN
Classifier: License :: OSI Approved :: GNU General Public License v3 or later (GPLv3+)
